idt/__init__.py
idt/__main__.py
idt/bing.py
idt/bing_api.py
idt/duckgo.py
idt/factories.py
idt/flickr_api.py
idt/resizers/__init__.py
idt/resizers/get_resizer.py
idt/resizers/longer_side.py
idt/resizers/shorter_side.py
idt/resizers/smartcrop.py
idt/utils/__init__.py
idt/utils/create_dataset_csv.py
idt/utils/download_images.py
idt/utils/remove_corrupt.py
idt/utils/remove_duplicates.py
idt/utils/split_dataset.py
idt-0.0.6.dist-info/LICENSE
idt-0.0.6.dist-info/METADATA
idt-0.0.6.dist-info/WHEEL
idt-0.0.6.dist-info/dependency_links.txt
idt-0.0.6.dist-info/entry_points.txt
idt-0.0.6.dist-info/top_level.txt
idt-0.0.6.dist-info/RECORD
