Metadata-Version: 2.1
Name: idt
Version: 0.0.6
Summary: A cli tool that quickly generates ready-to-use image datasets
Home-page: https://github.com/deliton/idt
Author: Deliton Junior
Author-email: deliton.m@hotmail.com
License: MIT
Download-URL: https://github.com/deliton/idt/archive/master.zip
Platform: UNKNOWN
Classifier: License :: OSI Approved :: MIT License
Classifier: Programming Language :: Python :: 2.7
Classifier: Programming Language :: Python :: 3
Classifier: Programming Language :: Python :: 3.7
Requires-Python: >=2.7
Requires-Dist: Pillow (==7.0.0)
Requires-Dist: PyYAML (==5.3.1)
Requires-Dist: click (==7.1.2)
Requires-Dist: numpy (==1.19.1)
Requires-Dist: requests (==2.22.0)
Requires-Dist: rich (==6.1.2)
